pipeline_csv_gazprom_infotech/__init__.py
pipeline_csv_gazprom_infotech/diam.py
pipeline_csv_gazprom_infotech-1.4.dist-info/LICENSE
pipeline_csv_gazprom_infotech-1.4.dist-info/METADATA
pipeline_csv_gazprom_infotech-1.4.dist-info/WHEEL
pipeline_csv_gazprom_infotech-1.4.dist-info/top_level.txt
pipeline_csv_gazprom_infotech-1.4.dist-info/RECORD
