Metadata-Version: 2.1
Name: pipeline-csv-gazprom-infotech
Version: 1.4
Summary: Library for convert pipeline.csv file to Infotech XML.
Home-page: https://github.com/vb64/pipeline.csv
Author: Vitaly Bogomolov
Author-email: mail@vitaly-bogomolov.ru
License: UNKNOWN
Project-URL: Bug Tracker, https://github.com/vb64/pipeline.csv/issues
Platform: UNKNOWN
Classifier: Programming Language :: Python :: 3
Classifier: License :: OSI Approved :: MIT License
Classifier: Operating System :: OS Independent
Requires-Python: >=3.6
Requires-Dist: pipeline-csv>=1.20
Requires-Dist: pipeline-gazprom-infotech==1.3
